[{"name":"Al Anbār","shortCode":"AN"},{"name":"Al Başrah","shortCode":"BA"},{"name":"Al Muthanná","shortCode":"MU"},{"name":"Al Qādisīyah","shortCode":"QA"},{"name":"An Najaf","shortCode":"NA"},{"name":"Arbīl","shortCode":"AR"},{"name":"As Sulaymānīyah","shortCode":"SU"},{"name":"Bābil","shortCode":"BB"},{"name":"Baghdād","shortCode":"BG"},{"name":"Dohuk","shortCode":"DA"},{"name":"Dhī Qār","shortCode":"DQ"},{"name":"Diyālá","shortCode":"DI"},{"name":"Karbalā'","shortCode":"KA"},{"name":"Kirkuk","shortCode":"KI"},{"name":"Maysān","shortCode":"MA"},{"name":"Nīnawá","shortCode":"NI"},{"name":"Şalāḩ ad Dīn","shortCode":"SD"},{"name":"Wāsiţ","shortCode":"WA"}]